	<current_observation>
		<credit>Weather Underground NOAA Weather Station</credit>
		<credit_URL>http://wunderground.com/</credit_URL>
<termsofservice link="http://www.wunderground.com/weather/api/d/terms.html">This feed will be deprecated. Please switch to http://www.wunderground.com/weather/api/</termsofservice>
		<image>
		<url>http://icons.wxug.com/graphics/wu2/logo_130x80.png</url>
		<title>Weather Underground</title>
		<link>http://wunderground.com/</link>
		</image>
  <display_location>
  <full>Tallahassee, FL</full>
  <city>Tallahassee</city>
  <state>FL</state>
  <state_name>Florida</state_name>
  <country>US</country>
  <country_iso3166>US</country_iso3166>
  <zip>32301</zip>
  <latitude>30.42930031</latitude>
  <longitude>-84.25710297</longitude>
  <elevation>59.00000000 ft</elevation>
  </display_location>
		<observation_location>
		<full>Tallahassee, Florida</full>
		<city>Tallahassee</city>
		<state>Florida</state>
		<country>US</country>
		<country_iso3166>US</country_iso3166>
		<latitude>30.39353943</latitude>
		<longitude>-84.35134888</longitude>
		<elevation>52 ft</elevation>
		</observation_location>
		<station_id>KTLH</station_id>
		<observation_time>Last Updated on October 8, 3:53 AM EDT</observation_time>
		<observation_time_rfc822>Thu, 08 Oct 2015 07:53:00 GMT</observation_time_rfc822>
		<observation_epoch>1444290780</observation_epoch>
		<local_time>October 8, 4:05 AM EDT</local_time>
		<local_time_rfc822>Thu, 08 Oct 2015 08:05:56 GMT</local_time_rfc822>
		<local_epoch>1444291556</local_epoch>
		<weather>Clear</weather>
		<temperature_string>61 F (16 C)</temperature_string>
		<temp_f>61</temp_f>
		<temp_c>16</temp_c>
		<relative_humidity>87%</relative_humidity>
		<wind_string>Calm</wind_string>
		<wind_dir>North</wind_dir>
		<wind_degrees>0</wind_degrees>
		<wind_mph>0</wind_mph>
		<wind_gust_mph></wind_gust_mph>
		<pressure_string>30.04 in (1017 mb)</pressure_string>
		<pressure_mb>1017</pressure_mb>
		<pressure_in>30.04</pressure_in>
		<dewpoint_string>57 F (14 C)</dewpoint_string>
		<dewpoint_f>57</dewpoint_f>
		<dewpoint_c>14</dewpoint_c>
		
		<heat_index_string>NA</heat_index_string>
		<heat_index_f>NA</heat_index_f>
		<heat_index_c>NA</heat_index_c>
		
		
		<windchill_string>NA</windchill_string>
		<windchill_f>NA</windchill_f>
		<windchill_c>NA</windchill_c>
		
		<visibility_mi>10.0</visibility_mi>
		<visibility_km>16.1</visibility_km>
		<icons>
			<icon_set name="Default">
				<icon_url>http://icons.wxug.com/i/c/a/clear.gif</icon_url>
			</icon_set>
			<icon_set name="Smiley">
				<icon_url>http://icons.wxug.com/i/c/b/clear.gif</icon_url>
			</icon_set>
			<icon_set name="Generic">
				<icon_url>http://icons.wxug.com/i/c/c/clear.gif</icon_url>
			</icon_set>
			<icon_set name="Old School">
				<icon_url>http://icons.wxug.com/i/c/d/clear.gif</icon_url>
			</icon_set>
			<icon_set name="Cartoon">
				<icon_url>http://icons.wxug.com/i/c/e/clear.gif</icon_url>
			</icon_set>
			<icon_set name="Mobile">
				<icon_url>http://icons.wxug.com/i/c/f/clear.gif</icon_url>
			</icon_set>
			<icon_set name="Simple">
				<icon_url>http://icons.wxug.com/i/c/g/clear.gif</icon_url>
			</icon_set>
			<icon_set name="Contemporary">
				<icon_url>http://icons.wxug.com/i/c/h/clear.gif</icon_url>
			</icon_set>
			<icon_set name="Helen">
				<icon_url>http://icons.wxug.com/i/c/i/clear.gif</icon_url>
			</icon_set>
			<icon_set name="Incredible">
				<icon_url>http://icons.wxug.com/i/c/k/clear.gif</icon_url>
			</icon_set>
		</icons>
		<icon_url_base>http://icons.wxug.com/graphics/conds/</icon_url_base>
		<icon_url_name>.GIF</icon_url_name>
		<icon>clear</icon>
		<forecast_url>http://www.wunderground.com/US/FL/Tallahassee.html</forecast_url>
		<history_url>http://www.wunderground.com/history/airport/KTLH/2015/10/8/DailyHistory.html</history_url>
		<ob_url>http://www.wunderground.com/cgi-bin/findweather/getForecast?query=30.39353943,-84.35134888</ob_url>
	</current_observation>
